inkhinge/__init__.py
inkhinge/core.py
inkhinge-1.0.6.dist-info/licenses/LICENSE
inkhinge-1.0.6.dist-info/METADATA
inkhinge-1.0.6.dist-info/WHEEL
inkhinge-1.0.6.dist-info/top_level.txt
inkhinge-1.0.6.dist-info/RECORD
