Metadata-Version: 2.4
Name: inkhinge
Version: 1.0.6
Summary: The next-generation deep learning toolkit designed specifically for spectral analysis
Home-page: https://github.com/1412universe/inkhinge
Author: Fenglong Li,Siyang Li,Kehan Li,Zhiqing Guo
Author-email: 15340666394@163.com
Project-URL: Bug Tracker, https://github.com/1412universe/inkhinge/issues
Classifier: Programming Language :: Python :: 3
Classifier: License :: OSI Approved :: MIT License
Classifier: Operating System :: OS Independent
Requires-Python: >=3.9
License-File: LICENSE
Dynamic: license-file
